{
	"$schema": "https://raw.githubusercontent.com/xen-42/outer-wilds-new-horizons/main/NewHorizons/Schemas/body_schema.json",
	"name": "TimberHearth",
	"Base": {
		"gravityFallOff": "linear"
	},
	"MapMarker": {
		"minDisplayDistanceOverride": -1.0,
		"maxDisplayDistanceOverride": -1.0
	},
	"Orbit": {
		"orbitLineFadeEndDistance": -1.0,
		"orbitLineFadeStartDistance": -1.0
	},
	"Props": {
		"details": [
			{
				"path": "Prefab_NOM_Whiteboard_Shared/PedestalAnchor/Prefab_NOM_SharedPedestal",
				"rotation": {
					"x": 67.44015,
					"y": 263.16626,
					"z": 277.59375
				},
				"alignRadial": false,
				"position": {
					"x": -52.6514053,
					"y": 14.1671753,
					"z": 218.565948
				},
				"isRelativeToParent": true,
				"parentPath": "Sector_TH"
			},
			{
				"path": "ConstructionYardIsland_Body/Sector_ConstructionYard/Interactables_ConstructionYard/OrbitalControl/Prefab_NOM_Whiteboard_Shared/Props_NOM_Whiteboard_Shared",
				"rotation": {
					"x": 86.8973846,
					"y": 325.6225,
					"z": 339.502533
				},
				"alignRadial": false,
				"position": {
					"x": -53.54754,
					"y": 16.32819,
					"z": 218.232132
				},
				"isRelativeToParent": true,
				"parentPath": "Sector_TH"
			}
		],
		"dialogue": [
			{
				"pathToExistingDialogue": "Sector_TH/Sector_Village/Sector_StartingCamp/Characters_StartingCamp/Villager_HEA_Slate/ConversationZone_RSci",
				"radius": 1.0,
				"xmlFile": "C:\\Users\\japlo\\AppData\\Roaming\\OuterWildsModManager\\OWML\\Mods\\theo-retical.RogueOracle\\text\\Slate.xml",
				"flashlightToggle": "none"
			}
		],
		"translatorText": [
			{
				"arcInfo": [
					{
						"type": "adult"
					},
					{
						"type": "adult"
					},
					{
						"type": "adult"
					},
					{
						"type": "adult"
					},
					{
						"type": "adult"
					},
					{
						"type": "adult"
					},
					{
						"type": "adult"
					},
					{
						"type": "adult"
					},
					{
						"type": "adult"
					}
				],
				"seed": 1,
				"type": "wall",
				"location": "a",
				"xmlFile": "C:\\Users\\japlo\\AppData\\Roaming\\OuterWildsModManager\\OWML\\Mods\\theo-retical.RogueOracle\\text\\Observatory_Wall.xml",
				"rotation": {},
				"isRelativeToParent": true,
				"parentPath": "Sector_TH/Props_NOM_Whiteboard_Shared"
			}
		],
		"signals": [
			{
				"detectionRadius": 100.0,
				"frequency": "Relic",
				"name": "Oracle Signal",
				"reveals": "oracle_museum_device",
				"audio": "C:\\Users\\japlo\\AppData\\Roaming\\OuterWildsModManager\\OWML\\Mods\\theo-retical.RogueOracle\\assets\\aliens.mp3",
				"maxDistance": 30.0,
				"position": {
					"y": 0.5
				},
				"isRelativeToParent": true,
				"parentPath": "Sector_TH/Prefab_NOM_SharedPedestal"
			}
		]
	},
	"ReferenceFrame": {},
	"ShipLog": {
		"xmlFile": "planets/timber_log.xml"
	},
	"ShockEffect": {}
}